MANIFEST.in
setup.cfg
setup.py
wordfish/__init__.py
wordfish/analysis.py
wordfish/browser.py
wordfish/corpus.py
wordfish/hello.py
wordfish/interface.py
wordfish/models.py
wordfish/nlp.py
wordfish/plugin.py
wordfish/terms.py
wordfish/utils.py
wordfish/vm.py
wordfish.egg-info/PKG-INFO
wordfish.egg-info/SOURCES.txt
wordfish.egg-info/dependency_links.txt
wordfish.egg-info/entry_points.txt
wordfish.egg-info/not-zip-safe
wordfish.egg-info/pbr.json
wordfish.egg-info/requires.txt
wordfish.egg-info/top_level.txt
wordfish/plugins/README.md
wordfish/plugins/__init__.py
wordfish/plugins/__init__.pyc
wordfish/scripts/__init__.py
wordfish/scripts/run_analysis.py
wordfish/scripts/run_slurm.py
wordfish/standards/__init__.py
wordfish/standards/owl/__init__.py
wordfish/standards/owl/functions.py
wordfish/standards/xml/__init__.py
wordfish/standards/xml/functions.py
wordfish/static/bootstrap/css/bootstrap-theme.css
wordfish/static/bootstrap/css/bootstrap-theme.css.map
wordfish/static/bootstrap/css/bootstrap-theme.min.css
wordfish/static/bootstrap/css/bootstrap.css
wordfish/static/bootstrap/css/bootstrap.css.map
wordfish/static/bootstrap/css/bootstrap.min.css
wordfish/static/bootstrap/fonts/glyphicons-halflings-regular.eot
wordfish/static/bootstrap/fonts/glyphicons-halflings-regular.svg
wordfish/static/bootstrap/fonts/glyphicons-halflings-regular.ttf
wordfish/static/bootstrap/fonts/glyphicons-halflings-regular.woff
wordfish/static/bootstrap/fonts/glyphicons-halflings-regular.woff2
wordfish/static/bootstrap/js/bootstrap.js
wordfish/static/bootstrap/js/bootstrap.min.js
wordfish/static/bootstrap/js/npm.js
wordfish/static/css/form-elements.css
wordfish/static/css/style.css
wordfish/static/font-awesome/css/font-awesome.css
wordfish/static/font-awesome/css/font-awesome.min.css
wordfish/static/font-awesome/fonts/FontAwesome.otf
wordfish/static/font-awesome/fonts/fontawesome-webfont.eot
wordfish/static/font-awesome/fonts/fontawesome-webfont.svg
wordfish/static/font-awesome/fonts/fontawesome-webfont.ttf
wordfish/static/font-awesome/fonts/fontawesome-webfont.woff
wordfish/static/font-awesome/fonts/fontawesome-webfont.woff2
wordfish/static/font-awesome/less/animated.less
wordfish/static/font-awesome/less/bordered-pulled.less
