Metadata-Version: 1.0
Name: wordfish
Version: 1.1.3
Summary: Infrastructure for finding relationships between terms in corpus of interest.
Home-page: http://www.github.com/word-fish/wordfish-python
Author: Poldracklab
Author-email: vsochat@stanford.edu
License: LICENSE.txt
Keywords: wordfish,nlp,text parsing
Platform: UNKNOWN
